{
	"backtraceGraph" : 
	{
		"commands" : 
		[
			"install",
			"sfml_add_library"
		],
		"files" : 
		[
			"_deps/sfml-src/cmake/Macros.cmake",
			"_deps/sfml-src/src/SFML/Graphics/CMakeLists.txt"
		],
		"nodes" : 
		[
			{
				"file" : 1
			},
			{
				"command" : 1,
				"file" : 1,
				"line" : 88,
				"parent" : 0
			},
			{
				"command" : 0,
				"file" : 0,
				"line" : 234,
				"parent" : 1
			},
			{
				"command" : 0,
				"file" : 0,
				"line" : 246,
				"parent" : 1
			},
			{
				"command" : 0,
				"file" : 0,
				"line" : 268,
				"parent" : 1
			}
		]
	},
	"installers" : 
	[
		{
			"backtrace" : 2,
			"component" : "devel",
			"destination" : "lib",
			"paths" : 
			[
				"_deps/sfml-build/lib/RelWithDebInfo/libsfml-graphics-s.a"
			],
			"targetId" : "sfml-graphics::@98af38147d5fa7e70f61",
			"targetIndex" : 2,
			"type" : "target"
		},
		{
			"backtrace" : 3,
			"component" : "Unspecified",
			"destination" : "lib/pkgconfig",
			"paths" : 
			[
				"_deps/sfml-build/src/SFML/Graphics/tools/pkg-config/sfml-graphics.pc"
			],
			"type" : "file"
		},
		{
			"backtrace" : 4,
			"component" : "devel",
			"destination" : "lib/cmake/SFML",
			"paths" : 
			[
				"_deps/sfml-build/src/SFML/Graphics/SFMLGraphicsDependencies.cmake"
			],
			"type" : "file"
		}
	],
	"paths" : 
	{
		"build" : "_deps/sfml-build/src/SFML/Graphics",
		"source" : "_deps/sfml-src/src/SFML/Graphics"
	}
}
