{
	"configurations" : 
	[
		{
			"directories" : 
			[
				{
					"build" : ".",
					"childIndexes" : 
					[
						1
					],
					"hasInstallRule" : true,
					"jsonFile" : "directory-.-Debug-f5ebdc15457944623624.json",
					"minimumCMakeVersion" : 
					{
						"string" : "3.28"
					},
					"projectIndex" : 0,
					"source" : ".",
					"targetIndexes" : 
					[
						0
					]
				},
				{
					"build" : "_deps/sfml-build",
					"childIndexes" : 
					[
						2
					],
					"hasInstallRule" : true,
					"jsonFile" : "directory-_deps.sfml-build-Debug-141da1ff82b94d33f0d6.json",
					"minimumCMakeVersion" : 
					{
						"string" : "3.22"
					},
					"parentIndex" : 0,
					"projectIndex" : 1,
					"source" : "build/Desktop_Qt_6_9_1/_deps/sfml-src"
				},
				{
					"build" : "_deps/sfml-build/src/SFML",
					"childIndexes" : 
					[
						3,
						4,
						5,
						6,
						7
					],
					"hasInstallRule" : true,
					"jsonFile" : "directory-_deps.sfml-build.src.SFML-Debug-e4f37a2c34042277ab6e.json",
					"minimumCMakeVersion" : 
					{
						"string" : "3.22"
					},
					"parentIndex" : 1,
					"projectIndex" : 1,
					"source" : "build/Desktop_Qt_6_9_1/_deps/sfml-src/src/SFML"
				},
				{
					"build" : "_deps/sfml-build/src/SFML/System",
					"hasInstallRule" : true,
					"jsonFile" : "directory-_deps.sfml-build.src.SFML.System-Debug-3e50fc2f9ccd1272f923.json",
					"minimumCMakeVersion" : 
					{
						"string" : "3.22"
					},
					"parentIndex" : 2,
					"projectIndex" : 1,
					"source" : "build/Desktop_Qt_6_9_1/_deps/sfml-src/src/SFML/System",
					"targetIndexes" : 
					[
						4
					]
				},
				{
					"build" : "_deps/sfml-build/src/SFML/Window",
					"hasInstallRule" : true,
					"jsonFile" : "directory-_deps.sfml-build.src.SFML.Window-Debug-94654cd346e4f2aaf308.json",
					"minimumCMakeVersion" : 
					{
						"string" : "3.22"
					},
					"parentIndex" : 2,
					"projectIndex" : 1,
					"source" : "build/Desktop_Qt_6_9_1/_deps/sfml-src/src/SFML/Window",
					"targetIndexes" : 
					[
						5
					]
				},
				{
					"build" : "_deps/sfml-build/src/SFML/Network",
					"hasInstallRule" : true,
					"jsonFile" : "directory-_deps.sfml-build.src.SFML.Network-Debug-4dea6d3b3260ac298042.json",
					"minimumCMakeVersion" : 
					{
						"string" : "3.22"
					},
					"parentIndex" : 2,
					"projectIndex" : 1,
					"source" : "build/Desktop_Qt_6_9_1/_deps/sfml-src/src/SFML/Network",
					"targetIndexes" : 
					[
						3
					]
				},
				{
					"build" : "_deps/sfml-build/src/SFML/Graphics",
					"hasInstallRule" : true,
					"jsonFile" : "directory-_deps.sfml-build.src.SFML.Graphics-Debug-4dbc7f1dd9b0afc945f2.json",
					"minimumCMakeVersion" : 
					{
						"string" : "3.22"
					},
					"parentIndex" : 2,
					"projectIndex" : 1,
					"source" : "build/Desktop_Qt_6_9_1/_deps/sfml-src/src/SFML/Graphics",
					"targetIndexes" : 
					[
						2
					]
				},
				{
					"build" : "_deps/sfml-build/src/SFML/Audio",
					"hasInstallRule" : true,
					"jsonFile" : "directory-_deps.sfml-build.src.SFML.Audio-Debug-5e643fcc175bf9442c68.json",
					"minimumCMakeVersion" : 
					{
						"string" : "3.22"
					},
					"parentIndex" : 2,
					"projectIndex" : 1,
					"source" : "build/Desktop_Qt_6_9_1/_deps/sfml-src/src/SFML/Audio",
					"targetIndexes" : 
					[
						1
					]
				}
			],
			"name" : "Debug",
			"projects" : 
			[
				{
					"childIndexes" : 
					[
						1
					],
					"directoryIndexes" : 
					[
						0
					],
					"name" : "CMakeSFMLProject",
					"targetIndexes" : 
					[
						0
					]
				},
				{
					"directoryIndexes" : 
					[
						1,
						2,
						3,
						4,
						5,
						6,
						7
					],
					"name" : "SFML",
					"parentIndex" : 0,
					"targetIndexes" : 
					[
						1,
						2,
						3,
						4,
						5
					]
				}
			],
			"targets" : 
			[
				{
					"directoryIndex" : 0,
					"id" : "main::@6890427a1f51a3e7e1df",
					"jsonFile" : "target-main-Debug-a332db65bb05fb18e426.json",
					"name" : "main",
					"projectIndex" : 0
				},
				{
					"directoryIndex" : 7,
					"id" : "sfml-audio::@a153e5727587c53fce98",
					"jsonFile" : "target-sfml-audio-Debug-9e11db807078e644bf77.json",
					"name" : "sfml-audio",
					"projectIndex" : 1
				},
				{
					"directoryIndex" : 6,
					"id" : "sfml-graphics::@98af38147d5fa7e70f61",
					"jsonFile" : "target-sfml-graphics-Debug-1206ef2669a3d914c284.json",
					"name" : "sfml-graphics",
					"projectIndex" : 1
				},
				{
					"directoryIndex" : 5,
					"id" : "sfml-network::@d7f79968b2699e7782cb",
					"jsonFile" : "target-sfml-network-Debug-650827ec4d08dde2156d.json",
					"name" : "sfml-network",
					"projectIndex" : 1
				},
				{
					"directoryIndex" : 3,
					"id" : "sfml-system::@8cb1db2982443611e568",
					"jsonFile" : "target-sfml-system-Debug-b0a1d8016cbafb0ceb25.json",
					"name" : "sfml-system",
					"projectIndex" : 1
				},
				{
					"directoryIndex" : 4,
					"id" : "sfml-window::@5730451e331e3690ae65",
					"jsonFile" : "target-sfml-window-Debug-6cdd8f9697c1fe014dd7.json",
					"name" : "sfml-window",
					"projectIndex" : 1
				}
			]
		},
		{
			"directories" : 
			[
				{
					"build" : ".",
					"childIndexes" : 
					[
						1
					],
					"hasInstallRule" : true,
					"jsonFile" : "directory-.-Release-f5ebdc15457944623624.json",
					"minimumCMakeVersion" : 
					{
						"string" : "3.28"
					},
					"projectIndex" : 0,
					"source" : ".",
					"targetIndexes" : 
					[
						0
					]
				},
				{
					"build" : "_deps/sfml-build",
					"childIndexes" : 
					[
						2
					],
					"hasInstallRule" : true,
					"jsonFile" : "directory-_deps.sfml-build-Release-141da1ff82b94d33f0d6.json",
					"minimumCMakeVersion" : 
					{
						"string" : "3.22"
					},
					"parentIndex" : 0,
					"projectIndex" : 1,
					"source" : "build/Desktop_Qt_6_9_1/_deps/sfml-src"
				},
				{
					"build" : "_deps/sfml-build/src/SFML",
					"childIndexes" : 
					[
						3,
						4,
						5,
						6,
						7
					],
					"hasInstallRule" : true,
					"jsonFile" : "directory-_deps.sfml-build.src.SFML-Release-e4f37a2c34042277ab6e.json",
					"minimumCMakeVersion" : 
					{
						"string" : "3.22"
					},
					"parentIndex" : 1,
					"projectIndex" : 1,
					"source" : "build/Desktop_Qt_6_9_1/_deps/sfml-src/src/SFML"
				},
				{
					"build" : "_deps/sfml-build/src/SFML/System",
					"hasInstallRule" : true,
					"jsonFile" : "directory-_deps.sfml-build.src.SFML.System-Release-2203695330afb541a6a5.json",
					"minimumCMakeVersion" : 
					{
						"string" : "3.22"
					},
					"parentIndex" : 2,
					"projectIndex" : 1,
					"source" : "build/Desktop_Qt_6_9_1/_deps/sfml-src/src/SFML/System",
					"targetIndexes" : 
					[
						4
					]
				},
				{
					"build" : "_deps/sfml-build/src/SFML/Window",
					"hasInstallRule" : true,
					"jsonFile" : "directory-_deps.sfml-build.src.SFML.Window-Release-b5767b8a3b20cae19f81.json",
					"minimumCMakeVersion" : 
					{
						"string" : "3.22"
					},
					"parentIndex" : 2,
					"projectIndex" : 1,
					"source" : "build/Desktop_Qt_6_9_1/_deps/sfml-src/src/SFML/Window",
					"targetIndexes" : 
					[
						5
					]
				},
				{
					"build" : "_deps/sfml-build/src/SFML/Network",
					"hasInstallRule" : true,
					"jsonFile" : "directory-_deps.sfml-build.src.SFML.Network-Release-8105bbb7b1c7cac10df3.json",
					"minimumCMakeVersion" : 
					{
						"string" : "3.22"
					},
					"parentIndex" : 2,
					"projectIndex" : 1,
					"source" : "build/Desktop_Qt_6_9_1/_deps/sfml-src/src/SFML/Network",
					"targetIndexes" : 
					[
						3
					]
				},
				{
					"build" : "_deps/sfml-build/src/SFML/Graphics",
					"hasInstallRule" : true,
					"jsonFile" : "directory-_deps.sfml-build.src.SFML.Graphics-Release-1004b113b38ba6ab9292.json",
					"minimumCMakeVersion" : 
					{
						"string" : "3.22"
					},
					"parentIndex" : 2,
					"projectIndex" : 1,
					"source" : "build/Desktop_Qt_6_9_1/_deps/sfml-src/src/SFML/Graphics",
					"targetIndexes" : 
					[
						2
					]
				},
				{
					"build" : "_deps/sfml-build/src/SFML/Audio",
					"hasInstallRule" : true,
					"jsonFile" : "directory-_deps.sfml-build.src.SFML.Audio-Release-9a17056abd4eb9604269.json",
					"minimumCMakeVersion" : 
					{
						"string" : "3.22"
					},
					"parentIndex" : 2,
					"projectIndex" : 1,
					"source" : "build/Desktop_Qt_6_9_1/_deps/sfml-src/src/SFML/Audio",
					"targetIndexes" : 
					[
						1
					]
				}
			],
			"name" : "Release",
			"projects" : 
			[
				{
					"childIndexes" : 
					[
						1
					],
					"directoryIndexes" : 
					[
						0
					],
					"name" : "CMakeSFMLProject",
					"targetIndexes" : 
					[
						0
					]
				},
				{
					"directoryIndexes" : 
					[
						1,
						2,
						3,
						4,
						5,
						6,
						7
					],
					"name" : "SFML",
					"parentIndex" : 0,
					"targetIndexes" : 
					[
						1,
						2,
						3,
						4,
						5
					]
				}
			],
			"targets" : 
			[
				{
					"directoryIndex" : 0,
					"id" : "main::@6890427a1f51a3e7e1df",
					"jsonFile" : "target-main-Release-495a55c1d7288a96a3a9.json",
					"name" : "main",
					"projectIndex" : 0
				},
				{
					"directoryIndex" : 7,
					"id" : "sfml-audio::@a153e5727587c53fce98",
					"jsonFile" : "target-sfml-audio-Release-ebf1875ac7e2f0ee0f11.json",
					"name" : "sfml-audio",
					"projectIndex" : 1
				},
				{
					"directoryIndex" : 6,
					"id" : "sfml-graphics::@98af38147d5fa7e70f61",
					"jsonFile" : "target-sfml-graphics-Release-2bec5f48df9c5ca2563d.json",
					"name" : "sfml-graphics",
					"projectIndex" : 1
				},
				{
					"directoryIndex" : 5,
					"id" : "sfml-network::@d7f79968b2699e7782cb",
					"jsonFile" : "target-sfml-network-Release-e43eb34b360ef3561b0e.json",
					"name" : "sfml-network",
					"projectIndex" : 1
				},
				{
					"directoryIndex" : 3,
					"id" : "sfml-system::@8cb1db2982443611e568",
					"jsonFile" : "target-sfml-system-Release-c4cc228ba049a98ea7ae.json",
					"name" : "sfml-system",
					"projectIndex" : 1
				},
				{
					"directoryIndex" : 4,
					"id" : "sfml-window::@5730451e331e3690ae65",
					"jsonFile" : "target-sfml-window-Release-f64379ae835299cf9b67.json",
					"name" : "sfml-window",
					"projectIndex" : 1
				}
			]
		},
		{
			"directories" : 
			[
				{
					"build" : ".",
					"childIndexes" : 
					[
						1
					],
					"hasInstallRule" : true,
					"jsonFile" : "directory-.-RelWithDebInfo-f5ebdc15457944623624.json",
					"minimumCMakeVersion" : 
					{
						"string" : "3.28"
					},
					"projectIndex" : 0,
					"source" : ".",
					"targetIndexes" : 
					[
						0
					]
				},
				{
					"build" : "_deps/sfml-build",
					"childIndexes" : 
					[
						2
					],
					"hasInstallRule" : true,
					"jsonFile" : "directory-_deps.sfml-build-RelWithDebInfo-141da1ff82b94d33f0d6.json",
					"minimumCMakeVersion" : 
					{
						"string" : "3.22"
					},
					"parentIndex" : 0,
					"projectIndex" : 1,
					"source" : "build/Desktop_Qt_6_9_1/_deps/sfml-src"
				},
				{
					"build" : "_deps/sfml-build/src/SFML",
					"childIndexes" : 
					[
						3,
						4,
						5,
						6,
						7
					],
					"hasInstallRule" : true,
					"jsonFile" : "directory-_deps.sfml-build.src.SFML-RelWithDebInfo-e4f37a2c34042277ab6e.json",
					"minimumCMakeVersion" : 
					{
						"string" : "3.22"
					},
					"parentIndex" : 1,
					"projectIndex" : 1,
					"source" : "build/Desktop_Qt_6_9_1/_deps/sfml-src/src/SFML"
				},
				{
					"build" : "_deps/sfml-build/src/SFML/System",
					"hasInstallRule" : true,
					"jsonFile" : "directory-_deps.sfml-build.src.SFML.System-RelWithDebInfo-33d3b5d53666c8af9b61.json",
					"minimumCMakeVersion" : 
					{
						"string" : "3.22"
					},
					"parentIndex" : 2,
					"projectIndex" : 1,
					"source" : "build/Desktop_Qt_6_9_1/_deps/sfml-src/src/SFML/System",
					"targetIndexes" : 
					[
						4
					]
				},
				{
					"build" : "_deps/sfml-build/src/SFML/Window",
					"hasInstallRule" : true,
					"jsonFile" : "directory-_deps.sfml-build.src.SFML.Window-RelWithDebInfo-6ad80d625f25e21e2602.json",
					"minimumCMakeVersion" : 
					{
						"string" : "3.22"
					},
					"parentIndex" : 2,
					"projectIndex" : 1,
					"source" : "build/Desktop_Qt_6_9_1/_deps/sfml-src/src/SFML/Window",
					"targetIndexes" : 
					[
						5
					]
				},
				{
					"build" : "_deps/sfml-build/src/SFML/Network",
					"hasInstallRule" : true,
					"jsonFile" : "directory-_deps.sfml-build.src.SFML.Network-RelWithDebInfo-1829e42105f9daf42577.json",
					"minimumCMakeVersion" : 
					{
						"string" : "3.22"
					},
					"parentIndex" : 2,
					"projectIndex" : 1,
					"source" : "build/Desktop_Qt_6_9_1/_deps/sfml-src/src/SFML/Network",
					"targetIndexes" : 
					[
						3
					]
				},
				{
					"build" : "_deps/sfml-build/src/SFML/Graphics",
					"hasInstallRule" : true,
					"jsonFile" : "directory-_deps.sfml-build.src.SFML.Graphics-RelWithDebInfo-8ab1bee8bd2fb8d74599.json",
					"minimumCMakeVersion" : 
					{
						"string" : "3.22"
					},
					"parentIndex" : 2,
					"projectIndex" : 1,
					"source" : "build/Desktop_Qt_6_9_1/_deps/sfml-src/src/SFML/Graphics",
					"targetIndexes" : 
					[
						2
					]
				},
				{
					"build" : "_deps/sfml-build/src/SFML/Audio",
					"hasInstallRule" : true,
					"jsonFile" : "directory-_deps.sfml-build.src.SFML.Audio-RelWithDebInfo-632bfccd99aca6dbbf43.json",
					"minimumCMakeVersion" : 
					{
						"string" : "3.22"
					},
					"parentIndex" : 2,
					"projectIndex" : 1,
					"source" : "build/Desktop_Qt_6_9_1/_deps/sfml-src/src/SFML/Audio",
					"targetIndexes" : 
					[
						1
					]
				}
			],
			"name" : "RelWithDebInfo",
			"projects" : 
			[
				{
					"childIndexes" : 
					[
						1
					],
					"directoryIndexes" : 
					[
						0
					],
					"name" : "CMakeSFMLProject",
					"targetIndexes" : 
					[
						0
					]
				},
				{
					"directoryIndexes" : 
					[
						1,
						2,
						3,
						4,
						5,
						6,
						7
					],
					"name" : "SFML",
					"parentIndex" : 0,
					"targetIndexes" : 
					[
						1,
						2,
						3,
						4,
						5
					]
				}
			],
			"targets" : 
			[
				{
					"directoryIndex" : 0,
					"id" : "main::@6890427a1f51a3e7e1df",
					"jsonFile" : "target-main-RelWithDebInfo-ac9bef593ac0c164216a.json",
					"name" : "main",
					"projectIndex" : 0
				},
				{
					"directoryIndex" : 7,
					"id" : "sfml-audio::@a153e5727587c53fce98",
					"jsonFile" : "target-sfml-audio-RelWithDebInfo-44299e5b49ab874833f5.json",
					"name" : "sfml-audio",
					"projectIndex" : 1
				},
				{
					"directoryIndex" : 6,
					"id" : "sfml-graphics::@98af38147d5fa7e70f61",
					"jsonFile" : "target-sfml-graphics-RelWithDebInfo-c4ad848718026988acfe.json",
					"name" : "sfml-graphics",
					"projectIndex" : 1
				},
				{
					"directoryIndex" : 5,
					"id" : "sfml-network::@d7f79968b2699e7782cb",
					"jsonFile" : "target-sfml-network-RelWithDebInfo-c7a9f5a6eee91662c9b8.json",
					"name" : "sfml-network",
					"projectIndex" : 1
				},
				{
					"directoryIndex" : 3,
					"id" : "sfml-system::@8cb1db2982443611e568",
					"jsonFile" : "target-sfml-system-RelWithDebInfo-c8b961739b99d874ece9.json",
					"name" : "sfml-system",
					"projectIndex" : 1
				},
				{
					"directoryIndex" : 4,
					"id" : "sfml-window::@5730451e331e3690ae65",
					"jsonFile" : "target-sfml-window-RelWithDebInfo-b6d3067b9633a7281e73.json",
					"name" : "sfml-window",
					"projectIndex" : 1
				}
			]
		}
	],
	"kind" : "codemodel",
	"paths" : 
	{
		"build" : "/home/louis/Documents/Projet Qt/cmake-sfml-project-master/build/Desktop_Qt_6_9_1",
		"source" : "/home/louis/Documents/Projet Qt/cmake-sfml-project-master"
	},
	"version" : 
	{
		"major" : 2,
		"minor" : 7
	}
}
